matplobblib/__init__.py
matplobblib/forall.py
matplobblib/aisd/AISD.py
matplobblib/aisd/__init__.py
matplobblib/aisd/additional_funcs.py
matplobblib/aisd/data_structures.py
matplobblib/aisd/search_algorythms.py
matplobblib/ml/__init__.py
matplobblib/ml/additional_funcs/__init__.py
matplobblib/ml/additional_funcs/b2_visual/__init__.py
matplobblib/ml/additional_funcs/b2_visual/b2_visual.py
matplobblib/ml/additional_funcs/file_handling/__init__.py
matplobblib/ml/additional_funcs/folds/__init__.py
matplobblib/ml/additional_funcs/folds/folds.py
matplobblib/ml/additional_funcs/math_funcs/__init__.py
matplobblib/ml/additional_funcs/math_funcs/math_funcs.py
matplobblib/ml/additional_funcs/metrics/__init__.py
matplobblib/ml/additional_funcs/metrics/metrics.py
matplobblib/ml/additional_funcs/plot_classification/__init__.py
matplobblib/ml/additional_funcs/plot_classification/plot_class.py
matplobblib/ml/knn/__init__.py
matplobblib/ml/knn/knn.py
matplobblib/ml/logreg/__init__.py
matplobblib/ml/logreg/cm.py
matplobblib/ml/nbc/__init__.py
matplobblib/ml/nbc/nbc.py
matplobblib/ml/randomforrest/__init__.py
matplobblib/ml/randomforrest/rf.py
matplobblib/ml/rm/__init__.py
matplobblib/ml/rm/rm.py
matplobblib/ml/svc/__init__.py
matplobblib/ml/svc/svcs.py
matplobblib/ml/tree/__init__.py
matplobblib/ml/tree/trees.py
matplobblib/nm/__init__.py
matplobblib/nm/additional_funcs/__init__.py
matplobblib/nm/base/__init__.py
matplobblib/nm/differential_eqs/__init__.py
matplobblib/nm/eigen/__init__.py
matplobblib/nm/eigen/jacobi/__init__.py
matplobblib/nm/eigen/qr/__init__.py
matplobblib/nm/eigen/vectors_from_values/__init__.py
matplobblib/nm/eqs/__init__.py
matplobblib/nm/fourier/__init__.py
matplobblib/nm/interp/__init__.py
matplobblib/nm/matrices/__init__.py
matplobblib/nm/matrices/SVD/__init__.py
matplobblib/nm/matrices/householder/__init__.py
matplobblib/nm/sistems/__init__.py
matplobblib/nm/strassen/__init__.py
matplobblib/nm/theory/__init__.py
matplobblib/nm/theory/html_parser.py
matplobblib-0.3.23.dist-info/licenses/LICENSE.txt
matplobblib-0.3.23.dist-info/METADATA
matplobblib-0.3.23.dist-info/WHEEL
matplobblib-0.3.23.dist-info/top_level.txt
matplobblib-0.3.23.dist-info/RECORD
