Metadata-Version: 2.4
Name: matplobblib
Version: 0.3.23
Summary: Just a library for some subjects
Home-page: https://github.com/Ackrome/matplobblib
Author: Ackrome
Author-email: ivansergeyevicht@gmail.com
License: MIT
Classifier: Programming Language :: Python :: 3
Classifier: License :: OSI Approved :: MIT License
Classifier: Operating System :: OS Independent
Requires-Python: >=3.6
License-File: LICENSE.txt
Requires-Dist: numpy
Requires-Dist: sympy
Requires-Dist: pandas
Requires-Dist: scipy
Requires-Dist: pyperclip
Requires-Dist: PyMuPDF
Requires-Dist: graphviz
Requires-Dist: statsmodels
Requires-Dist: cvxopt
Requires-Dist: beautifulsoup4
Requires-Dist: matplotlib
Requires-Dist: numba
Requires-Dist: IPython
Requires-Dist: tqdm
Requires-Dist: scikit-learn
Requires-Dist: scikit-image
Requires-Dist: requests
Requires-Dist: Pillow
Dynamic: author
Dynamic: author-email
Dynamic: classifier
Dynamic: description
Dynamic: description-content-type
Dynamic: home-page
Dynamic: license
Dynamic: license-file
Dynamic: requires-dist
Dynamic: requires-python
Dynamic: summary
